django_xworkflows/__init__.py
django_xworkflows/compat.py
django_xworkflows/models.py
django_xworkflows/locale/fr_FR/LC_MESSAGES/django.mo
django_xworkflows/locale/fr_FR/LC_MESSAGES/django.po
django_xworkflows/management/__init__.py
django_xworkflows/management/commands/__init__.py
django_xworkflows/management/commands/rebuild_transitionlog_states.py
django_xworkflows/xworkflow_log/__init__.py
django_xworkflows/xworkflow_log/admin.py
django_xworkflows/xworkflow_log/models.py
django_xworkflows/xworkflow_log/locale/fr_FR/LC_MESSAGES/django.mo
django_xworkflows/xworkflow_log/locale/fr_FR/LC_MESSAGES/django.po
django_xworkflows/xworkflow_log/migrations/0001_initial.py
django_xworkflows/xworkflow_log/migrations/__init__.py
django_xworkflows_3-0.12.3.1.dist-info/LICENSE
django_xworkflows_3-0.12.3.1.dist-info/METADATA
django_xworkflows_3-0.12.3.1.dist-info/WHEEL
django_xworkflows_3-0.12.3.1.dist-info/top_level.txt
django_xworkflows_3-0.12.3.1.dist-info/RECORD
