Metadata-Version: 2.1
Name: django-xworkflows-3
Version: 0.12.3.1
Summary: A django app enabling Django models to use xworkflows. Compatible with django 3
Home-page: https://github.com/lethe3000/django_xworkflows
Author: Raphaël Barrois
Author-email: raphael.barrois+django_xworkflows@polytechnique.org
License: BSD
Download-URL: http://pypi.python.org/pypi/django-xworkflows-3/
Keywords: django workflow state machine automaton
Platform: UNKNOWN
Classifier: Development Status :: 5 - Production/Stable
Classifier: Intended Audience :: Developers
Classifier: License :: OSI Approved :: BSD License
Classifier: Topic :: Software Development :: Libraries :: Python Modules
Classifier: Operating System :: OS Independent
Classifier: Programming Language :: Python
Classifier: Programming Language :: Python :: 2
Classifier: Programming Language :: Python :: 2.7
Classifier: Programming Language :: Python :: 3
Classifier: Programming Language :: Python :: 3.4
Classifier: Programming Language :: Python :: 3.5
Classifier: Programming Language :: Python :: 3.6
Requires-Dist: Django
Requires-Dist: xworkflows
